<annotation>
	<folder>Images</folder>
	<filename>img_187.jpg</filename>
	<path>img_187.jpg</path>
	<source>
		<database>Unknown</database>
	</source>
	<size>
		<width>2448</width>
		<height>3264</height>
		<depth>3</depth>
	</size>
	<segmented>0</segmented>
	<object>
		<name>Out-of-stock</name>
		<pose>Unspecified</pose>
		<truncated>0</truncated>
		<difficult>0</difficult>
		<bndbox>
			<xmin>832</xmin>
			<ymin>2556</ymin>
			<xmax>929</xmax>
			<ymax>2962</ymax>
		</bndbox>
	</object>
	<object>
		<name>Misplacement</name>
		<pose>Unspecified</pose>
		<truncated>0</truncated>
		<difficult>0</difficult>
		<bndbox>
			<xmin>1202</xmin>
			<ymin>2564</ymin>
			<xmax>1281</xmax>
			<ymax>2967</ymax>
		</bndbox>
	</object>
</annotation>
